quant_invest_lab/backtest.py
quant_invest_lab/constants.py
quant_invest_lab/data_provider.py
quant_invest_lab/indicators.py
quant_invest_lab/metrics.py
quant_invest_lab/optimization.py
quant_invest_lab/portfolio.py
quant_invest_lab/reports.py
quant_invest_lab/screener.py
quant_invest_lab/signal_processing.py
quant_invest_lab/simulation.py
quant_invest_lab/types.py
quant_invest_lab/utils.py
quant_invest_lab-0.2.11.dist-info/METADATA
quant_invest_lab-0.2.11.dist-info/WHEEL
quant_invest_lab-0.2.11.dist-info/RECORD
