Metadata-Version: 2.1
Name: quant-invest-lab
Version: 0.2.11
Summary: Quant Invest Lab is a python package to help you to do some quantitative experiments, while trying to learn or build quantitative investment solutions. This project was initially my own set of functionnalities but I decided to build a package for that and sharing it as open source project.
Home-page: https://github.com/BaptisteZloch/Quant-Invest-Lab
License: MIT
Keywords: trading,backtest,investments,portfolio,quantitative
Author: BaptisteZloch
Author-email: bzloch@hotmail.fr
Maintainer: BaptisteZloch
Maintainer-email: bzloch@hotmail.fr
Requires-Python: >=3.9,<3.12
Classifier: License :: OSI Approved :: MIT License
Classifier: Programming Language :: Python :: 3
Classifier: Programming Language :: Python :: 3.9
Classifier: Programming Language :: Python :: 3.10
Classifier: Programming Language :: Python :: 3.11
Classifier: Topic :: Office/Business :: Financial :: Investment
Classifier: Topic :: Software Development :: Build Tools
Classifier: Topic :: Software Development :: Libraries :: Python Modules
Requires-Dist: beautifulsoup4 (>=4.12.2,<5.0.0)
Requires-Dist: bokeh (>=3.2.2,<4.0.0)
Requires-Dist: emd-signal (>=1.4.0,<2.0.0)
Requires-Dist: fitter (>=1.5.2,<2.0.0)
Requires-Dist: kucoin-python (>=1.0.11,<2.0.0)
Requires-Dist: matplotlib (>=3.7.1,<4.0.0)
Requires-Dist: nbformat (>=5.8.0,<6.0.0)
Requires-Dist: numpy (>=1.23.5,<2.0.0)
Requires-Dist: pandas (>=1.5.3,<2.0.0)
Requires-Dist: plotly (>=5.14.1,<6.0.0)
Requires-Dist: pywavelets (>=1.4.1,<2.0.0)
Requires-Dist: scikit-learn (>=1.2.2,<2.0.0)
Requires-Dist: scipy (>=1.10.1,<2.0.0)
Requires-Dist: seaborn (>=0.12.2,<0.13.0)
Requires-Dist: statsmodels (>=0.14.0,<0.15.0)
Requires-Dist: ta (>=0.10.2,<0.11.0)
Requires-Dist: tqdm (>=4.64.1,<5.0.0)
Project-URL: Bug Tracker, https://github.com/BaptisteZloch/Quant-Invest-Lab/issues
Project-URL: Repository, https://github.com/BaptisteZloch/Quant-Invest-Lab
